<?xml version="1.0" encoding="utf-8" ?>
<dwsync>
<file name="lato-black.eot" server="D:/wampserver/www" local="130856390020000000" remote="130856390020000000" Dst="0" />
<file name="lato-black.woff" server="D:/wampserver/www" local="130856390020000000" remote="130856390020000000" Dst="0" />
<file name="lato-black.ttf" server="D:/wampserver/www" local="130856390020000000" remote="130856390020000000" Dst="0" />
<file name="lato-bold.eot" server="D:/wampserver/www" local="130856390020000000" remote="130856390020000000" Dst="0" />
<file name="lato-bold.woff" server="D:/wampserver/www" local="130856390020000000" remote="130856390020000000" Dst="0" />
<file name="lato-bold.ttf" server="D:/wampserver/www" local="130856390020000000" remote="130856390020000000" Dst="0" />
<file name="lato-bolditalic.eot" server="D:/wampserver/www" local="130856390020000000" remote="130856390020000000" Dst="0" />
<file name="lato-bolditalic.woff" server="D:/wampserver/www" local="130856390020000000" remote="130856390020000000" Dst="0" />
<file name="lato-bolditalic.ttf" server="D:/wampserver/www" local="130856390020000000" remote="130856390020000000" Dst="0" />
<file name="lato-italic.eot" server="D:/wampserver/www" local="130856390020000000" remote="130856390020000000" Dst="0" />
<file name="lato-italic.woff" server="D:/wampserver/www" local="130856390020000000" remote="130856390020000000" Dst="0" />
<file name="lato-italic.ttf" server="D:/wampserver/www" local="130856390020000000" remote="130856390020000000" Dst="0" />
<file name="lato-light.eot" server="D:/wampserver/www" local="130856390020000000" remote="130856390020000000" Dst="0" />
<file name="lato-light.woff" server="D:/wampserver/www" local="130856390020000000" remote="130856390020000000" Dst="0" />
<file name="lato-light.ttf" server="D:/wampserver/www" local="130856390020000000" remote="130856390020000000" Dst="0" />
<file name="lato-regular.eot" server="D:/wampserver/www" local="130856390020000000" remote="130856390020000000" Dst="0" />
<file name="lato-regular.woff" server="D:/wampserver/www" local="130856390020000000" remote="130856390020000000" Dst="0" />
<file name="lato-regular.ttf" server="D:/wampserver/www" local="130856390020000000" remote="130856390020000000" Dst="0" />
</dwsync>